frame_averaging_pytorch/__init__.py
frame_averaging_pytorch/frame_averaging.py
frame_averaging_pytorch-0.1.2.dist-info/METADATA
frame_averaging_pytorch-0.1.2.dist-info/WHEEL
frame_averaging_pytorch-0.1.2.dist-info/licenses/LICENSE
frame_averaging_pytorch-0.1.2.dist-info/RECORD
