Metadata-Version: 2.3
Name: frame-averaging-pytorch
Version: 0.1.2
Summary: Frame Averaging
Project-URL: Homepage, https://pypi.org/project/frame-averaging-pytorch/
Project-URL: Repository, https://github.com/lucidrains/frame-averaging-pytorch
Author-email: Phil Wang <lucidrains@gmail.com>
License: MIT License
License-File: LICENSE
Keywords: artificial intelligence,deep learning,geometric learning
Classifier: Development Status :: 4 - Beta
Classifier: Intended Audience :: Developers
Classifier: License :: OSI Approved :: MIT License
Classifier: Programming Language :: Python :: 3.9
Classifier: Topic :: Scientific/Engineering :: Artificial Intelligence
Requires-Python: >=3.9
Requires-Dist: einops>=0.8.0
Requires-Dist: torch>=2.0
Provides-Extra: examples
Provides-Extra: test
Requires-Dist: pytest; extra == 'test'
